{
   "name":  "Query", 
   "result": 0.022098,
   "timing": 0.022098,
   "cardinality": 0,
   "extra-info": "select count(*) from watdiv1052644, watdiv1052645, watdiv1052629, watdiv1052584, watdiv1052650, watdiv1052654 where watdiv1052644.s = watdiv1052645.s and watdiv1052645.s = watdiv1052629.s and watdiv1052629.s = watdiv1052584.s and watdiv1052584.s = watdiv1052650.s and watdiv1052650.s = watdiv1052654.s;PRAGMA profile_output = '../query_plans/ce_duckdb/1_original_with_aliases_threshold/watdiv_acyclic_201_12/run_2.json';", 
   "timings": [

   ],
   "children": [
    {
      "name": "RESULT_COLLECTOR",
      "timing":0.000001,
      "cardinality":0,
      "extra_info": "",
      "children": [
       {
         "name": "UNGROUPED_AGGREGATE",
         "timing":0.000090,
         "cardinality":1,
         "extra_info": "count_star()",
         "children": [
          {
            "name": "HASH_JOIN",
            "timing":0.011522,
            "cardinality":283955,
            "extra_info": "INNER\nwatdiv1052644.s = watdiv1052645.s\n\n[INFOSEPARATOR]\nBuild Min: 206051\nBuild Max: 870355\n\n[INFOSEPARATOR]\nEC: 226954\n",
            "children": [
             {
               "name": "SEQ_SCAN ",
               "timing":0.005934,
               "cardinality":3288999,
               "extra_info": "watdiv1052644\n[INFOSEPARATOR]\ns\n[INFOSEPARATOR]\nFilters: s>=206051 AND s<=870355 AND s IS NOT NULL\n\n[INFOSEPARATOR]\nEC: 3289307",
               "children": [
               ]
             }
,
             {
               "name": "HASH_JOIN",
               "timing":0.000437,
               "cardinality":8448,
               "extra_info": "INNER\nwatdiv1052584.s = watdiv1052654.s\n\n[INFOSEPARATOR]\nBuild Min: 206051\nBuild Max: 870355\n\n[INFOSEPARATOR]\nEC: 7495\n",
               "children": [
                {
                  "name": "SEQ_SCAN ",
                  "timing":0.000229,
                  "cardinality":111911,
                  "extra_info": "watdiv1052584\n[INFOSEPARATOR]\ns\n[INFOSEPARATOR]\nFilters: s>=206051 AND s<=870355 AND s IS NOT NULL\n\n[INFOSEPARATOR]\nEC: 136215",
                  "children": [
                  ]
                }
,
                {
                  "name": "HASH_JOIN",
                  "timing":0.000384,
                  "cardinality":7601,
                  "extra_info": "INNER\nwatdiv1052629.s = watdiv1052654.s\n\n[INFOSEPARATOR]\nBuild Min: 206051\nBuild Max: 870355\n\n[INFOSEPARATOR]\nEC: 5977\n",
                  "children": [
                   {
                     "name": "SEQ_SCAN ",
                     "timing":0.000156,
                     "cardinality":90998,
                     "extra_info": "watdiv1052629\n[INFOSEPARATOR]\ns\n[INFOSEPARATOR]\nFilters: s>=206051 AND s<=870355 AND s IS NOT NULL\n\n[INFOSEPARATOR]\nEC: 91004",
                     "children": [
                     ]
                   }
,
                   {
                     "name": "HASH_JOIN",
                     "timing":0.000378,
                     "cardinality":8420,
                     "extra_info": "INNER\nwatdiv1052650.s = watdiv1052654.s\n\n[INFOSEPARATOR]\nBuild Min: 206051\nBuild Max: 870355\n\n[INFOSEPARATOR]\nEC: 7135\n",
                     "children": [
                      {
                        "name": "SEQ_SCAN ",
                        "timing":0.000125,
                        "cardinality":69964,
                        "extra_info": "watdiv1052650\n[INFOSEPARATOR]\ns\n[INFOSEPARATOR]\nFilters: s>=206051 AND s<=870355 AND s IS NOT NULL\n\n[INFOSEPARATOR]\nEC: 69970",
                        "children": [
                        ]
                      }
,
                      {
                        "name": "HASH_JOIN",
                        "timing":0.000409,
                        "cardinality":12026,
                        "extra_info": "INNER\nwatdiv1052645.s = watdiv1052654.s\n\n[INFOSEPARATOR]\nBuild Min: 206051\nBuild Max: 870355\n\n[INFOSEPARATOR]\nEC: 11077\n",
                        "children": [
                         {
                           "name": "SEQ_SCAN ",
                           "timing":0.000105,
                           "cardinality":59778,
                           "extra_info": "watdiv1052645\n[INFOSEPARATOR]\ns\n[INFOSEPARATOR]\nFilters: s>=206051 AND s<=870355 AND s IS NOT NULL\n\n[INFOSEPARATOR]\nEC: 59784",
                           "children": [
                           ]
                         }
,
                         {
                           "name": "SEQ_SCAN ",
                           "timing":0.000018,
                           "cardinality":20128,
                           "extra_info": "watdiv1052654\n[INFOSEPARATOR]\ns\n[INFOSEPARATOR]\nEC: 20128",
                           "children": [
                           ]
                         }
                        ]
                      }
                     ]
                   }
                  ]
                }
               ]
             }
            ]
          }
         ]
       }
      ]
    }
   ]
}