{
   "name":  "Query", 
   "result": 0.079460,
   "timing": 0.079460,
   "cardinality": 0,
   "extra-info": "select count(*) from imdb1, imdb30, imdb119, imdb103 where imdb1.s = imdb30.s and imdb30.s = imdb119.s and imdb119.d = imdb103.s;PRAGMA profile_output = '../query_plans/ce_duckdb/2_original_with_aliases/job_acyclic_106_03/run_9.json';", 
   "timings": [

   ],
   "children": [
    {
      "name": "RESULT_COLLECTOR",
      "timing":0.000003,
      "cardinality":0,
      "extra_info": "",
      "children": [
       {
         "name": "UNGROUPED_AGGREGATE",
         "timing":0.000003,
         "cardinality":1,
         "extra_info": "count_star()",
         "children": [
          {
            "name": "HASH_JOIN",
            "timing":0.017213,
            "cardinality":51165,
            "extra_info": "INNER\nimdb1.s = imdb30.s\n\n[INFOSEPARATOR]\nEC: 8479\n",
            "children": [
             {
               "name": "SEQ_SCAN ",
               "timing":0.006740,
               "cardinality":578133,
               "extra_info": "imdb1\n[INFOSEPARATOR]\ns\n[INFOSEPARATOR]\nFilters: s>=19478245 AND s<=22175841 AND s IS NOT NULL\n\n[INFOSEPARATOR]\nEC: 1262722",
               "children": [
               ]
             }
,
             {
               "name": "HASH_JOIN",
               "timing":0.006453,
               "cardinality":25105,
               "extra_info": "INNER\nimdb30.s = imdb119.s\n\n[INFOSEPARATOR]\nEC: 7289\n",
               "children": [
                {
                  "name": "SEQ_SCAN ",
                  "timing":0.001151,
                  "cardinality":281938,
                  "extra_info": "imdb30\n[INFOSEPARATOR]\ns\n[INFOSEPARATOR]\nFilters: s>=19478245 AND s<=22175841 AND s IS NOT NULL\n\n[INFOSEPARATOR]\nEC: 353282",
                  "children": [
                  ]
                }
,
                {
                  "name": "HASH_JOIN",
                  "timing":0.020340,
                  "cardinality":37639,
                  "extra_info": "INNER\nimdb119.d = imdb103.s\n\n[INFOSEPARATOR]\nBuild Min: 80\nBuild Max: 199977\n\n[INFOSEPARATOR]\nEC: 22397\n",
                  "children": [
                   {
                     "name": "SEQ_SCAN ",
                     "timing":0.022791,
                     "cardinality":571880,
                     "extra_info": "imdb119\n[INFOSEPARATOR]\ns\nd\n[INFOSEPARATOR]\nFilters: d>=80 AND d<=199977 AND d IS NOT NULL\n\n[INFOSEPARATOR]\nEC: 7326771",
                     "children": [
                     ]
                   }
,
                   {
                     "name": "SEQ_SCAN ",
                     "timing":0.000009,
                     "cardinality":8593,
                     "extra_info": "imdb103\n[INFOSEPARATOR]\ns\n[INFOSEPARATOR]\nEC: 8593",
                     "children": [
                     ]
                   }
                  ]
                }
               ]
             }
            ]
          }
         ]
       }
      ]
    }
   ]
}