{
   "name":  "Query", 
   "result": 0.438369,
   "timing": 0.438369,
   "cardinality": 0,
   "extra-info": "select count(*) from imdb100, imdb2, imdb8, imdb78 where imdb100.d = imdb2.d and imdb2.d = imdb8.s and imdb8.s = imdb78.s;PRAGMA profile_output = '../query_plans/ce_duckdb/2_original_with_aliases/job_acyclic_105_87/run_8.json';", 
   "timings": [

   ],
   "children": [
    {
      "name": "RESULT_COLLECTOR",
      "timing":0.000001,
      "cardinality":0,
      "extra_info": "",
      "children": [
       {
         "name": "UNGROUPED_AGGREGATE",
         "timing":0.001843,
         "cardinality":1,
         "extra_info": "count_star()",
         "children": [
          {
            "name": "HASH_JOIN",
            "timing":0.360115,
            "cardinality":8047155,
            "extra_info": "INNER\nimdb100.d = imdb2.d\n\n[INFOSEPARATOR]\nEC: 31653\n",
            "children": [
             {
               "name": "SEQ_SCAN ",
               "timing":0.008773,
               "cardinality":4518480,
               "extra_info": "imdb100\n[INFOSEPARATOR]\nd\n[INFOSEPARATOR]\nFilters: d>=1559 AND d<=2525392 AND d IS NOT NULL\n\n[INFOSEPARATOR]\nEC: 4520446",
               "children": [
               ]
             }
,
             {
               "name": "HASH_JOIN",
               "timing":0.016100,
               "cardinality":86901,
               "extra_info": "INNER\nimdb8.s = imdb78.s\n\n[INFOSEPARATOR]\nEC: 8463\n",
               "children": [
                {
                  "name": "SEQ_SCAN ",
                  "timing":0.002534,
                  "cardinality":1401286,
                  "extra_info": "imdb8\n[INFOSEPARATOR]\ns\n[INFOSEPARATOR]\nFilters: s>=1559 AND s<=2525392 AND s IS NOT NULL\n\n[INFOSEPARATOR]\nEC: 1401902",
                  "children": [
                  ]
                }
,
                {
                  "name": "HASH_JOIN",
                  "timing":0.010769,
                  "cardinality":13555,
                  "extra_info": "INNER\nimdb2.d = imdb78.s\n\n[INFOSEPARATOR]\nEC: 7297\n",
                  "children": [
                   {
                     "name": "SEQ_SCAN ",
                     "timing":0.002284,
                     "cardinality":1332753,
                     "extra_info": "imdb2\n[INFOSEPARATOR]\nd\n[INFOSEPARATOR]\nFilters: d>=1559 AND d<=2525392 AND d IS NOT NULL\n\n[INFOSEPARATOR]\nEC: 1333580",
                     "children": [
                     ]
                   }
,
                   {
                     "name": "SEQ_SCAN ",
                     "timing":0.000008,
                     "cardinality":6614,
                     "extra_info": "imdb78\n[INFOSEPARATOR]\ns\n[INFOSEPARATOR]\nEC: 6614",
                     "children": [
                     ]
                   }
                  ]
                }
               ]
             }
            ]
          }
         ]
       }
      ]
    }
   ]
}