{
    "execution_time": 0.81892,
    "root": {
        "name": "AGGREGATE",
        "execution_time": 0.001196,
        "actual_rows": 1,
        "estimated_cardinality": null,
        "children": [
            {
                "name": "HASHJOIN",
                "execution_time": 0.170027,
                "actual_rows": 15411672,
                "estimated_cardinality": null,
                "children": [
                    {
                        "name": "HASHJOIN",
                        "execution_time": 0.14693,
                        "actual_rows": 7705836,
                        "estimated_cardinality": null,
                        "children": [
                            {
                                "name": "SEQUENTIALSCAN",
                                "execution_time": 0.007182,
                                "actual_rows": 4296992,
                                "estimated_cardinality": 4302340,
                                "children": [],
                                "relation": "dblp23",
                                "opt_filter": "s>=1206437 AND s<=3341100 AND s IS NOT NULL",
                                "projection": [
                                    {
                                        "table_name": "dblp23",
                                        "field_name": "s"
                                    }
                                ]
                            },
                            {
                                "name": "HASHJOIN",
                                "execution_time": 0.087107,
                                "actual_rows": 3823220,
                                "estimated_cardinality": null,
                                "children": [
                                    {
                                        "name": "SEQUENTIALSCAN",
                                        "execution_time": 0.004734,
                                        "actual_rows": 3823251,
                                        "estimated_cardinality": 3823259,
                                        "children": [],
                                        "relation": "dblp2",
                                        "opt_filter": "s<=3341100 AND s IS NOT NULL",
                                        "projection": [
                                            {
                                                "table_name": "dblp2",
                                                "field_name": "s"
                                            }
                                        ]
                                    },
                                    {
                                        "name": "HASHJOIN",
                                        "execution_time": 0.055807,
                                        "actual_rows": 2134627,
                                        "estimated_cardinality": null,
                                        "children": [
                                            {
                                                "name": "HASHJOIN",
                                                "execution_time": 0.065353,
                                                "actual_rows": 2134627,
                                                "estimated_cardinality": null,
                                                "children": [
                                                    {
                                                        "name": "SEQUENTIALSCAN",
                                                        "execution_time": 0.002202,
                                                        "actual_rows": 2134658,
                                                        "estimated_cardinality": 2134666,
                                                        "children": [],
                                                        "relation": "dblp8",
                                                        "opt_filter": "s<=3341100 AND s IS NOT NULL",
                                                        "projection": [
                                                            {
                                                                "table_name": "dblp8",
                                                                "field_name": "s"
                                                            }
                                                        ]
                                                    },
                                                    {
                                                        "name": "SEQUENTIALSCAN",
                                                        "execution_time": 0.000933,
                                                        "actual_rows": 2134627,
                                                        "estimated_cardinality": 2134627,
                                                        "children": [],
                                                        "relation": "dblp6",
                                                        "opt_filter": null,
                                                        "projection": [
                                                            {
                                                                "table_name": "dblp6",
                                                                "field_name": "s"
                                                            }
                                                        ]
                                                    }
                                                ],
                                                "condition": [
                                                    [
                                                        {
                                                            "table_name": "dblp8",
                                                            "field_name": "s"
                                                        },
                                                        {
                                                            "table_name": "dblp6",
                                                            "field_name": "s"
                                                        }
                                                    ]
                                                ]
                                            },
                                            {
                                                "name": "SEQUENTIALSCAN",
                                                "execution_time": 0.001975,
                                                "actual_rows": 2134658,
                                                "estimated_cardinality": 2134666,
                                                "children": [],
                                                "relation": "dblp7",
                                                "opt_filter": "s<=3341100 AND s IS NOT NULL",
                                                "projection": [
                                                    {
                                                        "table_name": "dblp7",
                                                        "field_name": "s"
                                                    }
                                                ]
                                            }
                                        ],
                                        "condition": [
                                            [
                                                {
                                                    "table_name": "dblp8",
                                                    "field_name": "s"
                                                },
                                                {
                                                    "table_name": "dblp7",
                                                    "field_name": "s"
                                                }
                                            ]
                                        ]
                                    }
                                ],
                                "condition": [
                                    [
                                        {
                                            "table_name": "dblp2",
                                            "field_name": "s"
                                        },
                                        {
                                            "table_name": "dblp6",
                                            "field_name": "s"
                                        }
                                    ]
                                ]
                            }
                        ],
                        "condition": [
                            [
                                {
                                    "table_name": "dblp23",
                                    "field_name": "s"
                                },
                                {
                                    "table_name": "dblp6",
                                    "field_name": "s"
                                }
                            ]
                        ]
                    },
                    {
                        "name": "SEQUENTIALSCAN",
                        "execution_time": 0.007,
                        "actual_rows": 4269291,
                        "estimated_cardinality": 5475762,
                        "children": [],
                        "relation": "dblp20",
                        "opt_filter": "s>=1206437 AND s<=3341100 AND s IS NOT NULL",
                        "projection": [
                            {
                                "table_name": "dblp20",
                                "field_name": "s"
                            }
                        ]
                    }
                ],
                "condition": [
                    [
                        {
                            "table_name": "dblp6",
                            "field_name": "s"
                        },
                        {
                            "table_name": "dblp20",
                            "field_name": "s"
                        }
                    ]
                ]
            }
        ],
        "group_by": null,
        "aggregate": [
            "count_star()"
        ]
    },
    "aliases": {
        "dblp8": "dblp8",
        "dblp2": "dblp2",
        "dblp7": "dblp7",
        "dblp20": "dblp20",
        "dblp6": "dblp6",
        "dblp23": "dblp23"
    }
}